khandy/__init__.py
khandy/dict_utils.py
khandy/draw_utils.py
khandy/feature_utils.py
khandy/file_io_utils.py
khandy/fs_utils.py
khandy/hash_utils.py
khandy/misc.py
khandy/numpy_utils.py
khandy/optional_pkgs.py
khandy/seq_utils.py
khandy/text_utils.py
khandy/time_utils.py
khandy/version.py
khandy/boxes/__init__.py
khandy/boxes/boxes.py
khandy/boxes/boxes_and_indices.py
khandy/boxes/boxes_clip.py
khandy/boxes/boxes_coder.py
khandy/boxes/boxes_convert.py
khandy/boxes/boxes_filter.py
khandy/boxes/boxes_overlap.py
khandy/boxes/boxes_transform.py
khandy/boxes/boxes_utils.py
khandy/image/__init__.py
khandy/image/align_and_crop.py
khandy/image/crop_or_pad.py
khandy/image/flip.py
khandy/image/image_hash.py
khandy/image/misc.py
khandy/image/resize.py
khandy/image/rotate.py
khandy/image/translate.py
khandy/label/__init__.py
khandy/label/detect.py
khandy/model/__init__.py
khandy/model/classifier.py
khandy/model/detector.py
khandy/model/extractor.py
khandy/points/__init__.py
khandy/points/pts_letterbox.py
khandy/points/pts_misc.py
khandy/points/pts_transform_scale.py
khandy-0.1.27.dist-info/METADATA
khandy-0.1.27.dist-info/WHEEL
khandy-0.1.27.dist-info/top_level.txt
khandy-0.1.27.dist-info/RECORD
