Metadata-Version: 2.4
Name: khandy
Version: 0.1.27
Summary: Handy Utilities for Computer Vision
Home-page: https://github.com/quarrying/khandy
Author: quarryman
Author-email: quarrying@qq.com
Maintainer: quarryman
Maintainer-email: quarrying@qq.com
License: MIT
Keywords: computer vision
Classifier: Development Status :: 4 - Beta
Classifier: License :: OSI Approved :: MIT License
Classifier: Operating System :: OS Independent
Classifier: Topic :: Utilities
Requires-Python: >=3.7
Requires-Dist: numpy>=1.11.1
Requires-Dist: opencv-python
Requires-Dist: pillow
Requires-Dist: lxml
Requires-Dist: requests
Dynamic: author
Dynamic: author-email
Dynamic: classifier
Dynamic: description
Dynamic: description-content-type
Dynamic: home-page
Dynamic: keywords
Dynamic: license
Dynamic: maintainer
Dynamic: maintainer-email
Dynamic: requires-dist
Dynamic: requires-python
Dynamic: summary
